ips_util/__init__.py
ips_util/__main__.py
ips_util/patch.py
ips_util-1.0.dist-info/LICENSE
ips_util-1.0.dist-info/METADATA
ips_util-1.0.dist-info/WHEEL
ips_util-1.0.dist-info/entry_points.txt
ips_util-1.0.dist-info/top_level.txt
ips_util-1.0.dist-info/RECORD
