Metadata-Version: 2.1
Name: ips-util
Version: 1.0
Summary: A Python package for manipulating IPS patches
Home-page: https://github.com/nleseul/ips_util
Author: NLeseul
Author-email: nleseul@this-life.us
License: Unlicense
Platform: UNKNOWN
Classifier: Development Status :: 5 - Production/Stable
Classifier: Environment :: Console
Classifier: License :: Freeware
Classifier: Natural Language :: English
Classifier: Programming Language :: Python :: 3.2
Classifier: Topic :: Utilities
Requires-Python: >=3.2
